cinfo_jk/__init__.py
cinfo_jk/cinfo_jk.py
cinfo_jk/lib/__init__.py
cinfo_jk-0.1.dist-info/METADATA
cinfo_jk-0.1.dist-info/WHEEL
cinfo_jk-0.1.dist-info/entry_points.txt
cinfo_jk-0.1.dist-info/top_level.txt
cinfo_jk-0.1.dist-info/RECORD
